{
  "name": "oHordeBreeder",
  "sprite": "sHordeBreederIdle",
  "visible": true,
  "solid": false,
  "depth": -10,
  "persistent": false,
  "parent_id": null,
  "texture_mask_id": null,
  "uses_physics": false,
  "is_sensor": false,
  "collision_shape": 0,
  "density": 0.5,
  "restitution": 0.1,
  "group": 0,
  "linear_damping": 0.1,
  "angular_damping": 0.1,
  "friction": 0.2,
  "awake": true,
  "kinematic": true,
  "physics_vertices": [],
  "events": [
    [
      {
        "event_subtype": 0,
        "actions": [
          {
            "lib_id": 0,
            "id": 0,
            "kind": 0,
            "use_relative": false,
            "is_question": false,
            "use_apply_to": false,
            "exe_type": 0,
            "action_name": null,
            "code_id": "gml_Object_oHordeBreeder_Create_9945",
            "argument_count": 0,
            "who": 0,
            "relative": false,
            "is_not": false
          }
        ]
      }
    ],
    [],
    [
      {
        "event_subtype": 0,
        "actions": [
          {
            "lib_id": 0,
            "id": 0,
            "kind": 0,
            "use_relative": false,
            "is_question": false,
            "use_apply_to": false,
            "exe_type": 0,
            "action_name": null,
            "code_id": "gml_Object_oHordeBreeder_Alarm_0_9946",
            "argument_count": 0,
            "who": 0,
            "relative": false,
            "is_not": false
          }
        ]
      },
      {
        "event_subtype": 10,
        "actions": [
          {
            "lib_id": 0,
            "id": 0,
            "kind": 0,
            "use_relative": false,
            "is_question": false,
            "use_apply_to": false,
            "exe_type": 0,
            "action_name": null,
            "code_id": "gml_Object_oHordeBreeder_Alarm_10_9947",
            "argument_count": 0,
            "who": 0,
            "relative": false,
            "is_not": false
          }
        ]
      },
      {
        "event_subtype": 11,
        "actions": [
          {
            "lib_id": 0,
            "id": 0,
            "kind": 0,
            "use_relative": false,
            "is_question": false,
            "use_apply_to": false,
            "exe_type": 0,
            "action_name": null,
            "code_id": "gml_Object_oHordeBreeder_Alarm_11_9948",
            "argument_count": 0,
            "who": 0,
            "relative": false,
            "is_not": false
          }
        ]
      },
      {
        "event_subtype": 1,
        "actions": [
          {
            "lib_id": 0,
            "id": 0,
            "kind": 0,
            "use_relative": false,
            "is_question": false,
            "use_apply_to": false,
            "exe_type": 0,
            "action_name": null,
            "code_id": "gml_Object_oHordeBreeder_Alarm_1_9971",
            "argument_count": 0,
            "who": 0,
            "relative": false,
            "is_not": false
          }
        ]
      },
      {
        "event_subtype": 2,
        "actions": [
          {
            "lib_id": 0,
            "id": 0,
            "kind": 0,
            "use_relative": false,
            "is_question": false,
            "use_apply_to": false,
            "exe_type": 0,
            "action_name": null,
            "code_id": "gml_Object_oHordeBreeder_Alarm_2_10205",
            "argument_count": 0,
            "who": 0,
            "relative": false,
            "is_not": false
          }
        ]
      }
    ],
    [
      {
        "event_subtype": 0,
        "actions": [
          {
            "lib_id": 0,
            "id": 0,
            "kind": 0,
            "use_relative": false,
            "is_question": false,
            "use_apply_to": false,
            "exe_type": 0,
            "action_name": null,
            "code_id": "gml_Object_oHordeBreeder_Step_9949",
            "argument_count": 0,
            "who": 0,
            "relative": false,
            "is_not": false
          }
        ]
      }
    ],
    [
      {
        "event_subtype": 267,
        "actions": [
          {
            "lib_id": 0,
            "id": 0,
            "kind": 0,
            "use_relative": false,
            "is_question": false,
            "use_apply_to": false,
            "exe_type": 0,
            "action_name": null,
            "code_id": "gml_Object_oHordeBreeder_Collision_9950",
            "argument_count": 0,
            "who": 0,
            "relative": false,
            "is_not": false
          }
        ]
      },
      {
        "event_subtype": 439,
        "actions": [
          {
            "lib_id": 0,
            "id": 0,
            "kind": 0,
            "use_relative": false,
            "is_question": false,
            "use_apply_to": false,
            "exe_type": 0,
            "action_name": null,
            "code_id": "gml_Object_oHordeBreeder_Collision_9951",
            "argument_count": 0,
            "who": 0,
            "relative": false,
            "is_not": false
          }
        ]
      },
      {
        "event_subtype": 440,
        "actions": [
          {
            "lib_id": 0,
            "id": 0,
            "kind": 0,
            "use_relative": false,
            "is_question": false,
            "use_apply_to": false,
            "exe_type": 0,
            "action_name": null,
            "code_id": "gml_Object_oHordeBreeder_Collision_9952",
            "argument_count": 0,
            "who": 0,
            "relative": false,
            "is_not": false
          }
        ]
      },
      {
        "event_subtype": 435,
        "actions": [
          {
            "lib_id": 0,
            "id": 0,
            "kind": 0,
            "use_relative": false,
            "is_question": false,
            "use_apply_to": false,
            "exe_type": 0,
            "action_name": null,
            "code_id": "gml_Object_oHordeBreeder_Collision_9953",
            "argument_count": 0,
            "who": 0,
            "relative": false,
            "is_not": false
          }
        ]
      },
      {
        "event_subtype": 437,
        "actions": [
          {
            "lib_id": 0,
            "id": 0,
            "kind": 0,
            "use_relative": false,
            "is_question": false,
            "use_apply_to": false,
            "exe_type": 0,
            "action_name": null,
            "code_id": "gml_Object_oHordeBreeder_Collision_9954",
            "argument_count": 0,
            "who": 0,
            "relative": false,
            "is_not": false
          }
        ]
      },
      {
        "event_subtype": 382,
        "actions": [
          {
            "lib_id": 0,
            "id": 0,
            "kind": 0,
            "use_relative": false,
            "is_question": false,
            "use_apply_to": false,
            "exe_type": 0,
            "action_name": null,
            "code_id": "gml_Object_oHordeBreeder_Collision_9955",
            "argument_count": 0,
            "who": 0,
            "relative": false,
            "is_not": false
          }
        ]
      },
      {
        "event_subtype": 381,
        "actions": [
          {
            "lib_id": 0,
            "id": 0,
            "kind": 0,
            "use_relative": false,
            "is_question": false,
            "use_apply_to": false,
            "exe_type": 0,
            "action_name": null,
            "code_id": "gml_Object_oHordeBreeder_Collision_9956",
            "argument_count": 0,
            "who": 0,
            "relative": false,
            "is_not": false
          }
        ]
      }
    ],
    [],
    [],
    [
      {
        "event_subtype": 7,
        "actions": [
          {
            "lib_id": 0,
            "id": 0,
            "kind": 0,
            "use_relative": false,
            "is_question": false,
            "use_apply_to": false,
            "exe_type": 0,
            "action_name": null,
            "code_id": "gml_Object_oHordeBreeder_AniEnd_9957",
            "argument_count": 0,
            "who": 0,
            "relative": false,
            "is_not": false
          }
        ]
      },
      {
        "event_subtype": 10,
        "actions": [
          {
            "lib_id": 0,
            "id": 0,
            "kind": 0,
            "use_relative": false,
            "is_question": false,
            "use_apply_to": false,
            "exe_type": 0,
            "action_name": null,
            "code_id": "gml_Object_oHordeBreeder_User_0_9958",
            "argument_count": 0,
            "who": 0,
            "relative": false,
            "is_not": false
          }
        ]
      },
      {
        "event_subtype": 11,
        "actions": [
          {
            "lib_id": 0,
            "id": 0,
            "kind": 0,
            "use_relative": false,
            "is_question": false,
            "use_apply_to": false,
            "exe_type": 0,
            "action_name": null,
            "code_id": "gml_Object_oHordeBreeder_User_1_9959",
            "argument_count": 0,
            "who": 0,
            "relative": false,
            "is_not": false
          }
        ]
      },
      {
        "event_subtype": 12,
        "actions": [
          {
            "lib_id": 0,
            "id": 0,
            "kind": 0,
            "use_relative": false,
            "is_question": false,
            "use_apply_to": false,
            "exe_type": 0,
            "action_name": null,
            "code_id": "gml_Object_oHordeBreeder_User_2_9960",
            "argument_count": 0,
            "who": 0,
            "relative": false,
            "is_not": false
          }
        ]
      }
    ],
    [
      {
        "event_subtype": 0,
        "actions": [
          {
            "lib_id": 0,
            "id": 0,
            "kind": 0,
            "use_relative": false,
            "is_question": false,
            "use_apply_to": false,
            "exe_type": 0,
            "action_name": null,
            "code_id": "gml_Object_oHordeBreeder_Draw_9961",
            "argument_count": 0,
            "who": 0,
            "relative": false,
            "is_not": false
          }
        ]
      }
    ],
    [],
    [],
    [],
    [],
    [],
    []
  ]
}