{
  "name": "oHordeArea2",
  "sprite": "sHordeIdle",
  "visible": true,
  "solid": false,
  "depth": -3,
  "persistent": false,
  "parent_id": "oEnemy",
  "texture_mask_id": null,
  "uses_physics": false,
  "is_sensor": false,
  "collision_shape": 0,
  "density": 0.5,
  "restitution": 0.1,
  "group": 0,
  "linear_damping": 0.1,
  "angular_damping": 0.1,
  "friction": 0.2,
  "awake": true,
  "kinematic": true,
  "physics_vertices": [],
  "events": [
    [
      {
        "event_subtype": 0,
        "actions": [
          {
            "lib_id": 0,
            "id": 0,
            "kind": 0,
            "use_relative": false,
            "is_question": false,
            "use_apply_to": false,
            "exe_type": 0,
            "action_name": null,
            "code_id": "gml_Object_oHordeArea2_Create_9781",
            "argument_count": 0,
            "who": 0,
            "relative": false,
            "is_not": false
          }
        ]
      }
    ],
    [],
    [
      {
        "event_subtype": 0,
        "actions": [
          {
            "lib_id": 0,
            "id": 0,
            "kind": 0,
            "use_relative": false,
            "is_question": false,
            "use_apply_to": false,
            "exe_type": 0,
            "action_name": null,
            "code_id": "gml_Object_oHordeArea2_Alarm_0_9782",
            "argument_count": 0,
            "who": 0,
            "relative": false,
            "is_not": false
          }
        ]
      },
      {
        "event_subtype": 1,
        "actions": [
          {
            "lib_id": 0,
            "id": 0,
            "kind": 0,
            "use_relative": false,
            "is_question": false,
            "use_apply_to": false,
            "exe_type": 0,
            "action_name": null,
            "code_id": "gml_Object_oHordeArea2_Alarm_1_9783",
            "argument_count": 0,
            "who": 0,
            "relative": false,
            "is_not": false
          }
        ]
      },
      {
        "event_subtype": 2,
        "actions": [
          {
            "lib_id": 0,
            "id": 0,
            "kind": 0,
            "use_relative": false,
            "is_question": false,
            "use_apply_to": false,
            "exe_type": 0,
            "action_name": null,
            "code_id": "gml_Object_oHordeArea2_Alarm_2_9784",
            "argument_count": 0,
            "who": 0,
            "relative": false,
            "is_not": false
          }
        ]
      }
    ],
    [
      {
        "event_subtype": 0,
        "actions": [
          {
            "lib_id": 0,
            "id": 0,
            "kind": 0,
            "use_relative": false,
            "is_question": false,
            "use_apply_to": false,
            "exe_type": 0,
            "action_name": null,
            "code_id": "gml_Object_oHordeArea2_Step_0_9785",
            "argument_count": 0,
            "who": 0,
            "relative": false,
            "is_not": false
          }
        ]
      }
    ],
    [
      {
        "event_subtype": 381,
        "actions": [
          {
            "lib_id": 0,
            "id": 0,
            "kind": 0,
            "use_relative": false,
            "is_question": false,
            "use_apply_to": false,
            "exe_type": 0,
            "action_name": null,
            "code_id": "gml_Object_oHordeArea2_Collision_Screw_9788",
            "argument_count": 0,
            "who": 0,
            "relative": false,
            "is_not": false
          }
        ]
      },
      {
        "event_subtype": 382,
        "actions": [
          {
            "lib_id": 0,
            "id": 0,
            "kind": 0,
            "use_relative": false,
            "is_question": false,
            "use_apply_to": false,
            "exe_type": 0,
            "action_name": null,
            "code_id": "gml_Object_oHordeArea2_Collision_Screw_9788",
            "argument_count": 0,
            "who": 0,
            "relative": false,
            "is_not": false
          }
        ]
      },
      {
        "event_subtype": 293,
        "actions": [
          {
            "lib_id": 0,
            "id": 0,
            "kind": 0,
            "use_relative": false,
            "is_question": false,
            "use_apply_to": false,
            "exe_type": 0,
            "action_name": null,
            "code_id": "Horde_jump_higher_9797",
            "argument_count": 0,
            "who": 0,
            "relative": false,
            "is_not": false
          }
        ]
      }
    ],
    [],
    [],
    [
      {
        "event_subtype": 7,
        "actions": [
          {
            "lib_id": 0,
            "id": 0,
            "kind": 0,
            "use_relative": false,
            "is_question": false,
            "use_apply_to": false,
            "exe_type": 0,
            "action_name": null,
            "code_id": "gml_Object_oHordeArea2_Other_0_9786",
            "argument_count": 0,
            "who": 0,
            "relative": false,
            "is_not": false
          }
        ]
      },
      {
        "event_subtype": 26,
        "actions": [
          {
            "lib_id": 0,
            "id": 0,
            "kind": 0,
            "use_relative": false,
            "is_question": false,
            "use_apply_to": false,
            "exe_type": 0,
            "action_name": null,
            "code_id": "gml_Object_oHordeArea2_Other_1_9787",
            "argument_count": 0,
            "who": 0,
            "relative": false,
            "is_not": false
          }
        ]
      },
      {
        "event_subtype": 5,
        "actions": [
          {
            "lib_id": 0,
            "id": 0,
            "kind": 0,
            "use_relative": false,
            "is_question": false,
            "use_apply_to": false,
            "exe_type": 0,
            "action_name": null,
            "code_id": "gml_Object_Horde_RoomEnd_MusicStop_10119",
            "argument_count": 0,
            "who": 0,
            "relative": false,
            "is_not": false
          }
        ]
      }
    ],
    [],
    [],
    [],
    [],
    [],
    [],
    []
  ]
}